auto_rest/__init__.py
auto_rest/__main__.py
auto_rest/app.py
auto_rest/cli.py
auto_rest/handlers.py
auto_rest/interfaces.py
auto_rest/models.py
auto_rest/queries.py
auto_rest/routers.py
auto_rest_api-0.1.9.dist-info/LICENSE.md
auto_rest_api-0.1.9.dist-info/METADATA
auto_rest_api-0.1.9.dist-info/WHEEL
auto_rest_api-0.1.9.dist-info/entry_points.txt
auto_rest_api-0.1.9.dist-info/RECORD
